get_coordinates/__init__.py
get_coordinates/__main__.py
get_coordinates/boundaries/__init__.py
get_coordinates/boundaries/get_world_countries.py
get_coordinates/boundaries/world_countries.geojson
get_coordinates/utils/__init__.py
get_coordinates/utils/export.py
get_coordinates/utils/points.py
get_coordinates/utils/show.py
random_spatial_py-0.0.2.dist-info/LICENSE
random_spatial_py-0.0.2.dist-info/METADATA
random_spatial_py-0.0.2.dist-info/WHEEL
random_spatial_py-0.0.2.dist-info/top_level.txt
random_spatial_py-0.0.2.dist-info/RECORD
