Metadata-Version: 2.1
Name: random-spatial-py
Version: 0.0.2
Summary: Generate Random Spatial Assets
Home-page: https://github.com/SimonMolinsky/random-spatial-py
Author: Szymon Moliński
Author-email: simon@dataverselabs.com
License: MIT
Project-URL: Documentation, https://github.com/SimonMolinsky/random-spatial-py
Project-URL: Source, https://github.com/SimonMolinsky/random-spatial-py
Project-URL: Tracker, https://github.com/SimonMolinsky/random-spatial-py/issues
Classifier: Development Status :: 2 - Pre-Alpha
Classifier: Intended Audience :: Science/Research
Classifier: Topic :: Scientific/Engineering :: GIS
Classifier: License :: OSI Approved :: MIT License
Classifier: Programming Language :: Python :: 3.7
Classifier: Programming Language :: Python :: 3.8
Classifier: Programming Language :: Python :: 3.9
Classifier: Programming Language :: Python :: 3.10
Requires-Python: >=3.7
License-File: LICENSE
Requires-Dist: numpy
Requires-Dist: geopandas
Requires-Dist: matplotlib
